sphinx_cache/__init__.py
sphinx_cache/logging.py
sphinx_cache/setup.py
sphinx_cache/utils.py
sphinx_cache/version.py
sphinx_cache-0.0.1.dist-info/LICENSE
sphinx_cache-0.0.1.dist-info/METADATA
sphinx_cache-0.0.1.dist-info/WHEEL
sphinx_cache-0.0.1.dist-info/RECORD
