Metadata-Version: 2.1
Name: sphinx-cache
Version: 0.0.1
Summary: Sphinx extension for storing and restoring `.doctree` cache.
Home-page: https://github.com/useblocks/sphinx-cache
License: MIT
Author: team useblocks
Author-email: info@useblocks.com
Requires-Python: >=3.8.0,<4.0
Classifier: Development Status :: 2 - Pre-Alpha
Classifier: Intended Audience :: Developers
Classifier: License :: OSI Approved :: MIT License
Classifier: Operating System :: OS Independent
Classifier: Programming Language :: Python
Classifier: Programming Language :: Python :: 3
Classifier: Programming Language :: Python :: 3.8
Classifier: Programming Language :: Python :: 3.9
Classifier: Programming Language :: Python :: 3.10
Classifier: Programming Language :: Python :: 3.11
Classifier: Topic :: Documentation
Classifier: Topic :: Software Development :: Build Tools
Classifier: Topic :: Utilities
Requires-Dist: colorama (>=0.4.6)
Requires-Dist: pathlib (>=1.0.1)
Requires-Dist: sphinx (>=5.0)
Project-URL: Documentation, http://sphinx-cache.useblocks.com
Project-URL: Repository, https://github.com/useblocks/sphinx-cache
